Metadata-Version: 2.1
Name: gen-names-bsklodow
Version: 1.0.1
Summary: Generate random names with lenght
Home-page: https://github.com/treyhunner/names
Author: Bartosz Skłodowski
Author-email: sklodowski94@gmail.com
License: UNKNOWN
Keywords: random names
Platform: UNKNOWN
